quickcss/__init__.py
quickcss/_version.py
quickcss/clis/__init__.py
quickcss-0.0.1.data/scripts/quickcss
quickcss-0.0.1.dist-info/METADATA
quickcss-0.0.1.dist-info/WHEEL
quickcss-0.0.1.dist-info/top_level.txt
quickcss-0.0.1.dist-info/RECORD
