Metadata-Version: 2.1
Name: quickcss
Version: 0.0.1
Summary: A tool for quick CERN software setup
Author: Alkaid Cheng
Author-email: chi.lung.cheng@cern.ch
License: UNKNOWN
Platform: UNKNOWN
Classifier: Programming Language :: Python :: 3.6
Classifier: Programming Language :: Python :: 3.7
Classifier: Programming Language :: Python :: 3.8
Classifier: Programming Language :: Python :: 3.9
Classifier: License :: OSI Approved :: MIT License
Classifier: Operating System :: OS Independent
Requires-Python: >=3.6
Requires-Dist: click
